TS/TsPython.py
TS/__init__.py
Ascento-1.0.0.dist-info/METADATA
Ascento-1.0.0.dist-info/WHEEL
Ascento-1.0.0.dist-info/top_level.txt
Ascento-1.0.0.dist-info/RECORD
